event_marker-1.8.1.dist-info/licenses/LICENSE
src/__init__.py
src/__main__.py
src/cfg.py
src/cfg_window.py
src/csv_analysis_window.py
src/csv_window.py
src/event_manager.py
src/evt-config.yaml
src/gui.py
src/key_handler.py
src/marker_float.py
src/markers_widget.py
src/ol_logging.py
src/playback_controller.py
src/qivideo_widget.py
src/recover_from_print.py
event_marker-1.8.1.dist-info/METADATA
event_marker-1.8.1.dist-info/WHEEL
event_marker-1.8.1.dist-info/entry_points.txt
event_marker-1.8.1.dist-info/top_level.txt
event_marker-1.8.1.dist-info/RECORD
